bugswarm_client-2024.8.26-py3.8-nspkg.pth
bugswarm/client/__init__.py
bugswarm/client/bugswarm.py
bugswarm/client/command.py
bugswarm/client/docker.py
bugswarm_client-2024.8.26.dist-info/LICENSE
bugswarm_client-2024.8.26.dist-info/METADATA
bugswarm_client-2024.8.26.dist-info/WHEEL
bugswarm_client-2024.8.26.dist-info/entry_points.txt
bugswarm_client-2024.8.26.dist-info/namespace_packages.txt
bugswarm_client-2024.8.26.dist-info/top_level.txt
bugswarm_client-2024.8.26.dist-info/RECORD
