Metadata-Version: 2.1
Name: bugswarm-client
Version: 2024.8.26
Summary: The official command line client for the BugSwarm artifact dataset
Home-page: https://github.com/BugSwarm/bugswarm
Author: BugSwarm
Author-email: dev.bugswarm@gmail.com
Classifier: Programming Language :: Python :: 3
Classifier: License :: OSI Approved :: BSD License
License-File: LICENSE
Requires-Dist: click ==6.7
Requires-Dist: requests >=2.20.0
Requires-Dist: bugswarm-common
